setup.py
mlsm/__init__.py
mlsm/mlsm.py
mlsm.egg-info/PKG-INFO
mlsm.egg-info/SOURCES.txt
mlsm.egg-info/dependency_links.txt
mlsm.egg-info/requires.txt
mlsm.egg-info/top_level.txt