Metadata-Version: 1.1
Name: mlsm
Version: 0.0.4
Summary: Implementation of multiple data science models
Home-page: https://github.com/rh-marketingops/mlsm
Author: Jeremiah Coleman
Author-email: colemanja91@gmail.com
License: GNU General Public License
Keywords: data science lead scoring marketing automation
Platform: any
Classifier: Programming Language :: Python
Classifier: Development Status :: 4 - Beta
Classifier: Natural Language :: English
Classifier: Environment :: Web Environment
Classifier: Intended Audience :: Developers
Classifier: License :: OSI Approved :: Apache Software License
Classifier: Operating System :: OS Independent
Classifier: Topic :: Software Development :: Libraries :: Python Modules
Classifier: Topic :: Software Development :: Libraries :: Application Frameworks
